{
  "partners":[
    {
      "firstName":"Pamela",
      "lastName":"Giannone",
      "email":"pgiannone@hubspotpartners.com",
      "country":"United States",
      "availableDates":[
        "2017-06-07",
        "2017-06-13",
        "2017-06-14",
        "2017-06-15",
        "2017-06-17",
        "2017-06-19",
        "2017-06-20",
        "2017-06-22",
        "2017-06-26"
      ]
    },
    {
      "firstName":"Dahlia",
      "lastName":"Monica",
      "email":"dmonica@hubspotpartners.com",
      "country":"United States",
      "availableDates":[
        "2017-06-07",
        "2017-06-10",
        "2017-06-11",
        "2017-06-13",
        "2017-06-14",
        "2017-06-16",
        "2017-06-20",
        "2017-06-22"
      ]
    },
    {
      "firstName":"Genevie",
      "lastName":"Burn",
      "email":"gburn@hubspotpartners.com",
      "country":"United States",
      "availableDates":[
        "2017-06-13",
        "2017-06-14",
        "2017-06-16",
        "2017-06-17",
        "2017-06-19"
      ]
    },
    {
      "firstName":"Jonah",
      "lastName":"Livingstone",
      "email":"jlivingstone@hubspotpartners.com",
      "country":"United States",
      "availableDates":[
        "2017-06-10",
        "2017-06-11",
        "2017-06-13",
        "2017-06-14",
        "2017-06-17",
        "2017-06-21",
        "2017-06-22",
        "2017-06-23"
      ]
    },
    {
      "firstName":"Lachelle",
      "lastName":"Hitson",
      "email":"lhitson@hubspotpartners.com",
      "country":"United States",
      "availableDates":[
        "2017-06-11",
        "2017-06-13",
        "2017-06-14",
        "2017-06-15",
        "2017-06-18",
        "2017-06-19",
        "2017-06-28",
        "2017-07-01"
      ]
    },
    {
      "firstName":"Digna",
      "lastName":"Brosnan",
      "email":"dbrosnan@hubspotpartners.com",
      "country":"United States",
      "availableDates":[
        "2017-06-11",
        "2017-06-13",
        "2017-06-14",
        "2017-06-19",
        "2017-06-20",
        "2017-06-23"
      ]
    },
    {
      "firstName":"Marva",
      "lastName":"Kittel",
      "email":"mkittel@hubspotpartners.com",
      "country":"United States",
      "availableDates":[
        "2017-06-09",
        "2017-06-13",
        "2017-06-14",
        "2017-06-16",
        "2017-06-17",
        "2017-06-18",
        "2017-06-19",
        "2017-06-22",
        "2017-06-25"
      ]
    },
    {
      "firstName":"Arianne",
      "lastName":"Phebus",
      "email":"aphebus@hubspotpartners.com",
      "country":"United States",
      "availableDates":[
        "2017-06-11",
        "2017-06-13",
        "2017-06-14",
        "2017-06-18",
        "2017-06-20",
        "2017-06-21",
        "2017-06-23"
      ]
    },
    {
      "firstName":"Effie",
      "lastName":"Corriere",
      "email":"ecorriere@hubspotpartners.com",
      "country":"United States",
      "availableDates":[
        "2017-06-13",
        "2017-06-14",
        "2017-06-16",
        "2017-06-22",
        "2017-06-23"
      ]
    },
    {
      "firstName":"Evalyn",
      "lastName":"Szyszka",
      "email":"eszyszka@hubspotpartners.com",
      "country":"United States",
      "availableDates":[
        "2017-06-09",
        "2017-06-13",
        "2017-06-14",
        "2017-06-15",
        "2017-06-16",
        "2017-06-17",
        "2017-06-20",
        "2017-06-21",
        "2017-06-25",
        "2017-06-26"
      ]
    },
    {
      "firstName":"Linh",
      "lastName":"Ketelsen",
      "email":"lketelsen@hubspotpartners.com",
      "country":"United States",
      "availableDates":[
        "2017-06-08",
        "2017-06-11",
        "2017-06-13",
        "2017-06-14",
        "2017-06-17",
        "2017-06-18",
        "2017-06-19",
        "2017-06-23",
        "2017-06-24",
        "2017-06-25"
      ]
    },
    {
      "firstName":"Bruce",
      "lastName":"Nadel",
      "email":"bnadel@hubspotpartners.com",
      "country":"United States",
      "availableDates":[
        "2017-06-13",
        "2017-06-14",
        "2017-06-18",
        "2017-06-26"
      ]
    },
    {
      "firstName":"Oralee",
      "lastName":"Poteat",
      "email":"opoteat@hubspotpartners.com",
      "country":"United States",
      "availableDates":[
        "2017-06-11",
        "2017-06-13",
        "2017-06-14",
        "2017-06-16",
        "2017-06-17",
        "2017-06-21",
        "2017-06-22"
      ]
    },
    {
      "firstName":"Nicolette",
      "lastName":"Ernzen",
      "email":"nernzen@hubspotpartners.com",
      "country":"United States",
      "availableDates":[
        "2017-06-08",
        "2017-06-09",
        "2017-06-13",
        "2017-06-14",
        "2017-06-21",
        "2017-06-23",
        "2017-06-24",
        "2017-06-26"
      ]
    },
    {
      "firstName":"Gary",
      "lastName":"Cherrette",
      "email":"gcherrette@hubspotpartners.com",
      "country":"United States",
      "availableDates":[
        "2017-06-08",
        "2017-06-11",
        "2017-06-13",
        "2017-06-14",
        "2017-06-15",
        "2017-06-21",
        "2017-06-22",
        "2017-06-23",
        "2017-06-30"
      ]
    },
    {
      "firstName":"Etta",
      "lastName":"Tabuena",
      "email":"etabuena@hubspotpartners.com",
      "country":"United States",
      "availableDates":[
        "2017-06-07",
        "2017-06-08",
        "2017-06-09",
        "2017-06-11",
        "2017-06-28"
      ]
    },
    {
      "firstName":"Loria",
      "lastName":"Bageant",
      "email":"lbageant@hubspotpartners.com",
      "country":"United States",
      "availableDates":[
        "2017-06-10",
        "2017-06-11",
        "2017-06-17",
        "2017-06-18",
        "2017-06-19",
        "2017-06-22",
        "2017-06-24"
      ]
    },
    {
      "firstName":"Tisha",
      "lastName":"Kellywood",
      "email":"tkellywood@hubspotpartners.com",
      "country":"United States",
      "availableDates":[
        "2017-06-15",
        "2017-06-16",
        "2017-06-17",
        "2017-06-19",
        "2017-06-23"
      ]
    },
    {
      "firstName":"Svetlana",
      "lastName":"Heyd",
      "email":"sheyd@hubspotpartners.com",
      "country":"United States",
      "availableDates":[
        "2017-06-07",
        "2017-06-11",
        "2017-06-19",
        "2017-06-20",
        "2017-06-24",
        "2017-06-26"
      ]
    },
    {
      "firstName":"Astrid",
      "lastName":"Munshi",
      "email":"amunshi@hubspotpartners.com",
      "country":"United States",
      "availableDates":[
        "2017-06-10",
        "2017-06-17",
        "2017-06-18",
        "2017-06-20",
        "2017-06-22",
        "2017-06-26"
      ]
    },
    {
      "firstName":"Corazon",
      "lastName":"Capriotti",
      "email":"ccapriotti@hubspotpartners.com",
      "country":"United States",
      "availableDates":[
        "2017-06-11",
        "2017-06-16",
        "2017-06-18",
        "2017-06-20",
        "2017-06-22",
        "2017-06-26",
        "2017-06-30"
      ]
    },
    {
      "firstName":"Tiffiny",
      "lastName":"Zaczek",
      "email":"tzaczek@hubspotpartners.com",
      "country":"United States",
      "availableDates":[
        "2017-06-09",
        "2017-06-10",
        "2017-06-15",
        "2017-06-16",
        "2017-06-18",
        "2017-06-23",
        "2017-06-25"
      ]
    },
    {
      "firstName":"Karima",
      "lastName":"Counselman",
      "email":"kcounselman@hubspotpartners.com",
      "country":"United States",
      "availableDates":[
        "2017-06-17",
        "2017-06-19",
        "2017-06-23",
        "2017-06-26"
      ]
    },
    {
      "firstName":"Monika",
      "lastName":"Huckabaa",
      "email":"mhuckabaa@hubspotpartners.com",
      "country":"United States",
      "availableDates":[
        "2017-06-07",
        "2017-06-10",
        "2017-06-17",
        "2017-06-19",
        "2017-06-22",
        "2017-06-24",
        "2017-07-01"
      ]
    },
    {
      "firstName":"Yuri",
      "lastName":"Korewdit",
      "email":"ykorewdit@hubspotpartners.com",
      "country":"United States",
      "availableDates":[
        "2017-06-07",
        "2017-06-17",
        "2017-06-19",
        "2017-06-20",
        "2017-06-22",
        "2017-06-23",
        "2017-06-26"
      ]
    },
    {
      "firstName":"Evelyne",
      "lastName":"Vanwingerden",
      "email":"evanwingerden@hubspotpartners.com",
      "country":"Ireland",
      "availableDates":[
        "2017-05-17",
        "2017-05-19",
        "2017-05-20",
        "2017-05-25",
        "2017-05-26",
        "2017-05-28",
        "2017-05-29",
        "2017-06-02",
        "2017-06-03"
      ]
    },
    {
      "firstName":"Kaitlyn",
      "lastName":"Shane",
      "email":"kshane@hubspotpartners.com",
      "country":"Ireland",
      "availableDates":[
        "2017-05-18",
        "2017-05-19",
        "2017-05-20",
        "2017-05-21",
        "2017-05-26",
        "2017-05-28",
        "2017-05-29",
        "2017-06-01",
        "2017-06-02",
        "2017-06-03"
      ]
    },
    {
      "firstName":"Margaretta",
      "lastName":"Busson",
      "email":"mbusson@hubspotpartners.com",
      "country":"Ireland",
      "availableDates":[
        "2017-05-19",
        "2017-05-20",
        "2017-05-22",
        "2017-05-30",
        "2017-06-01",
        "2017-06-02",
        "2017-06-03"
      ]
    },
    {
      "firstName":"Ja",
      "lastName":"Siurek",
      "email":"jsiurek@hubspotpartners.com",
      "country":"Ireland",
      "availableDates":[
        "2017-05-19",
        "2017-05-20",
        "2017-05-25",
        "2017-05-28",
        "2017-06-01",
        "2017-06-02",
        "2017-06-03"
      ]
    },
    {
      "firstName":"Chi",
      "lastName":"Sitler",
      "email":"csitler@hubspotpartners.com",
      "country":"Ireland",
      "availableDates":[
        "2017-05-15",
        "2017-05-17",
        "2017-05-19",
        "2017-05-20",
        "2017-05-22",
        "2017-05-23",
        "2017-05-28",
        "2017-05-29",
        "2017-06-02",
        "2017-06-03"
      ]
    },
    {
      "firstName":"Corina",
      "lastName":"Sparlin",
      "email":"csparlin@hubspotpartners.com",
      "country":"Ireland",
      "availableDates":[
        "2017-05-19",
        "2017-05-20",
        "2017-05-22",
        "2017-06-02",
        "2017-06-03"
      ]
    },
    {
      "firstName":"Rickie",
      "lastName":"Mungia",
      "email":"rmungia@hubspotpartners.com",
      "country":"Ireland",
      "availableDates":[
        "2017-05-15",
        "2017-05-19",
        "2017-05-20",
        "2017-05-26",
        "2017-05-29",
        "2017-05-30",
        "2017-06-01",
        "2017-06-02",
        "2017-06-03"
      ]
    },
    {
      "firstName":"Kacie",
      "lastName":"Allain",
      "email":"kallain@hubspotpartners.com",
      "country":"Ireland",
      "availableDates":[
        "2017-05-15",
        "2017-05-17",
        "2017-05-19",
        "2017-05-20",
        "2017-05-21",
        "2017-05-22",
        "2017-05-30",
        "2017-06-01",
        "2017-06-02",
        "2017-06-03"
      ]
    },
    {
      "firstName":"Kaitlyn",
      "lastName":"Schoneck",
      "email":"kschoneck@hubspotpartners.com",
      "country":"Ireland",
      "availableDates":[
        "2017-05-17",
        "2017-05-19",
        "2017-05-20",
        "2017-05-22",
        "2017-05-25",
        "2017-05-30",
        "2017-06-01",
        "2017-06-02",
        "2017-06-03"
      ]
    },
    {
      "firstName":"Hoa",
      "lastName":"Morningstar",
      "email":"hmorningstar@hubspotpartners.com",
      "country":"Ireland",
      "availableDates":[
        "2017-05-17",
        "2017-05-19",
        "2017-05-20",
        "2017-05-21",
        "2017-05-22",
        "2017-05-25",
        "2017-05-30",
        "2017-06-02",
        "2017-06-03",
        "2017-06-05"
      ]
    },
    {
      "firstName":"Bernardina",
      "lastName":"Zoldesy",
      "email":"bzoldesy@hubspotpartners.com",
      "country":"Ireland",
      "availableDates":[
        "2017-05-16",
        "2017-05-17",
        "2017-05-19",
        "2017-05-20",
        "2017-05-21",
        "2017-05-25",
        "2017-05-26",
        "2017-05-28",
        "2017-06-02",
        "2017-06-03"
      ]
    },
    {
      "firstName":"Nila",
      "lastName":"Silverstein",
      "email":"nsilverstein@hubspotpartners.com",
      "country":"Ireland",
      "availableDates":[
        "2017-05-17",
        "2017-05-19",
        "2017-05-20",
        "2017-05-28",
        "2017-05-29",
        "2017-06-02",
        "2017-06-03"
      ]
    },
    {
      "firstName":"Fumiko",
      "lastName":"Nicols",
      "email":"fnicols@hubspotpartners.com",
      "country":"Ireland",
      "availableDates":[
        "2017-05-19",
        "2017-05-20",
        "2017-05-21",
        "2017-05-28",
        "2017-05-29",
        "2017-06-01",
        "2017-06-02",
        "2017-06-03"
      ]
    },
    {
      "firstName":"Lauralee",
      "lastName":"Toure",
      "email":"ltoure@hubspotpartners.com",
      "country":"Ireland",
      "availableDates":[
        "2017-05-19",
        "2017-05-20",
        "2017-05-21",
        "2017-05-24",
        "2017-05-28",
        "2017-06-02",
        "2017-06-03"
      ]
    },
    {
      "firstName":"Graciela",
      "lastName":"Luening",
      "email":"gluening@hubspotpartners.com",
      "country":"Ireland",
      "availableDates":[
        "2017-05-17",
        "2017-05-19",
        "2017-05-20",
        "2017-05-28",
        "2017-06-01",
        "2017-06-02",
        "2017-06-03"
      ]
    },
    {
      "firstName":"Magan",
      "lastName":"Rousselle",
      "email":"mrousselle@hubspotpartners.com",
      "country":"Ireland",
      "availableDates":[
        "2017-05-16",
        "2017-05-17",
        "2017-05-19",
        "2017-05-20",
        "2017-05-26",
        "2017-05-29",
        "2017-05-30",
        "2017-06-01",
        "2017-06-02",
        "2017-06-03",
        "2017-06-06",
        "2017-06-07"
      ]
    },
    {
      "firstName":"Priscilla",
      "lastName":"Kaluna",
      "email":"pkaluna@hubspotpartners.com",
      "country":"Ireland",
      "availableDates":[
        "2017-05-17",
        "2017-05-18",
        "2017-05-29"
      ]
    },
    {
      "firstName":"Gilma",
      "lastName":"Docker",
      "email":"gdocker@hubspotpartners.com",
      "country":"Ireland",
      "availableDates":[
        "2017-05-15",
        "2017-05-23",
        "2017-05-29"
      ]
    },
    {
      "firstName":"Thomas",
      "lastName":"Samowitz",
      "email":"tsamowitz@hubspotpartners.com",
      "country":"Ireland",
      "availableDates":[
        "2017-05-15",
        "2017-05-17",
        "2017-05-22",
        "2017-05-29",
        "2017-06-01"
      ]
    },
    {
      "firstName":"Jen",
      "lastName":"Landruth",
      "email":"jlandruth@hubspotpartners.com",
      "country":"Ireland",
      "availableDates":[
        "2017-05-16",
        "2017-05-30",
        "2017-06-07"
      ]
    },
    {
      "firstName":"Harriette",
      "lastName":"Krishna",
      "email":"hkrishna@hubspotpartners.com",
      "country":"Ireland",
      "availableDates":[
        "2017-05-17",
        "2017-05-28",
        "2017-05-29",
        "2017-05-30",
        "2017-06-01"
      ]
    },
    {
      "firstName":"Melia",
      "lastName":"Kinnunen",
      "email":"mkinnunen@hubspotpartners.com",
      "country":"Ireland",
      "availableDates":[
        "2017-05-17",
        "2017-05-22",
        "2017-05-26",
        "2017-06-01"
      ]
    },
    {
      "firstName":"Kaley",
      "lastName":"Dannenfelser",
      "email":"kdannenfelser@hubspotpartners.com",
      "country":"Ireland",
      "availableDates":[
        "2017-05-26",
        "2017-05-28",
        "2017-05-29",
        "2017-05-30",
        "2017-06-08"
      ]
    },
    {
      "firstName":"Teisha",
      "lastName":"Marionneaux",
      "email":"tmarionneaux@hubspotpartners.com",
      "country":"Ireland",
      "availableDates":[
        "2017-05-18",
        "2017-05-21",
        "2017-05-30"
      ]
    },
    {
      "firstName":"Timothy",
      "lastName":"Mastropietro",
      "email":"tmastropietro@hubspotpartners.com",
      "country":"Ireland",
      "availableDates":[
        "2017-05-17",
        "2017-05-22",
        "2017-05-23",
        "2017-05-25",
        "2017-05-28",
        "2017-05-30",
        "2017-06-06"
      ]
    },
    {
      "firstName":"Juan",
      "lastName":"Choy",
      "email":"jchoy@hubspotpartners.com",
      "country":"Ireland",
      "availableDates":[
        "2017-05-16",
        "2017-05-18",
        "2017-05-22",
        "2017-05-28",
        "2017-05-30"
      ]
    },
    {
      "firstName":"Yolande",
      "lastName":"Iwasa",
      "email":"yiwasa@hubspotpartners.com",
      "country":"Spain",
      "availableDates":[
        "2017-06-06",
        "2017-06-07",
        "2017-06-09",
        "2017-06-13",
        "2017-06-14",
        "2017-06-16",
        "2017-06-18",
        "2017-06-19",
        "2017-06-20",
        "2017-06-25"
      ]
    },
    {
      "firstName":"Tory",
      "lastName":"Partain",
      "email":"tpartain@hubspotpartners.com",
      "country":"Spain",
      "availableDates":[
        "2017-06-04",
        "2017-06-06",
        "2017-06-07",
        "2017-06-12",
        "2017-06-13",
        "2017-06-14",
        "2017-06-16",
        "2017-06-18",
        "2017-06-20"
      ]
    },
    {
      "firstName":"Charles",
      "lastName":"Schwerdtfeger",
      "email":"cschwerdtfeger@hubspotpartners.com",
      "country":"Spain",
      "availableDates":[
        "2017-06-05",
        "2017-06-06",
        "2017-06-07",
        "2017-06-11",
        "2017-06-13",
        "2017-06-14"
      ]
    },
    {
      "firstName":"Celinda",
      "lastName":"Ellery",
      "email":"cellery@hubspotpartners.com",
      "country":"Spain",
      "availableDates":[
        "2017-06-05",
        "2017-06-06",
        "2017-06-07",
        "2017-06-11",
        "2017-06-12",
        "2017-06-13",
        "2017-06-14",
        "2017-06-16"
      ]
    },
    {
      "firstName":"Debrah",
      "lastName":"Shuff",
      "email":"dshuff@hubspotpartners.com",
      "country":"Spain",
      "availableDates":[
        "2017-06-06",
        "2017-06-07",
        "2017-06-09",
        "2017-06-12",
        "2017-06-13",
        "2017-06-14",
        "2017-06-16",
        "2017-06-19",
        "2017-06-26"
      ]
    },
    {
      "firstName":"Shawnee",
      "lastName":"Oestreich",
      "email":"soestreich@hubspotpartners.com",
      "country":"Spain",
      "availableDates":[
        "2017-06-05",
        "2017-06-06",
        "2017-06-07",
        "2017-06-12",
        "2017-06-13",
        "2017-06-14",
        "2017-06-17",
        "2017-06-20",
        "2017-06-22",
        "2017-06-27"
      ]
    },
    {
      "firstName":"Rosia",
      "lastName":"Harelson",
      "email":"rharelson@hubspotpartners.com",
      "country":"Spain",
      "availableDates":[
        "2017-06-06",
        "2017-06-07",
        "2017-06-13",
        "2017-06-14",
        "2017-06-16",
        "2017-06-19",
        "2017-06-21"
      ]
    },
    {
      "firstName":"Lacy",
      "lastName":"Spellane",
      "email":"lspellane@hubspotpartners.com",
      "country":"Spain",
      "availableDates":[
        "2017-06-06",
        "2017-06-07",
        "2017-06-09",
        "2017-06-10",
        "2017-06-11",
        "2017-06-12",
        "2017-06-13",
        "2017-06-14",
        "2017-06-16",
        "2017-06-17",
        "2017-06-20",
        "2017-06-21"
      ]
    },
    {
      "firstName":"Jacquelin",
      "lastName":"Summarell",
      "email":"jsummarell@hubspotpartners.com",
      "country":"Spain",
      "availableDates":[
        "2017-06-06",
        "2017-06-07",
        "2017-06-12",
        "2017-06-13",
        "2017-06-14",
        "2017-06-20"
      ]
    },
    {
      "firstName":"Mireille",
      "lastName":"Ohs",
      "email":"mohs@hubspotpartners.com",
      "country":"Spain",
      "availableDates":[
        "2017-06-03",
        "2017-06-06",
        "2017-06-07",
        "2017-06-10",
        "2017-06-13",
        "2017-06-14",
        "2017-06-17",
        "2017-06-18"
      ]
    },
    {
      "firstName":"Doretta",
      "lastName":"Killingsworth",
      "email":"dkillingsworth@hubspotpartners.com",
      "country":"Spain",
      "availableDates":[
        "2017-06-03",
        "2017-06-05",
        "2017-06-06",
        "2017-06-07",
        "2017-06-11",
        "2017-06-13",
        "2017-06-14",
        "2017-06-16",
        "2017-06-17",
        "2017-06-18",
        "2017-06-19",
        "2017-06-20"
      ]
    },
    {
      "firstName":"Lorrie",
      "lastName":"Blondell",
      "email":"lblondell@hubspotpartners.com",
      "country":"Spain",
      "availableDates":[
        "2017-06-04",
        "2017-06-05",
        "2017-06-06",
        "2017-06-07",
        "2017-06-09",
        "2017-06-11",
        "2017-06-12",
        "2017-06-13",
        "2017-06-14",
        "2017-06-17",
        "2017-06-22"
      ]
    },
    {
      "firstName":"Christy",
      "lastName":"Polakis",
      "email":"cpolakis@hubspotpartners.com",
      "country":"Spain",
      "availableDates":[
        "2017-06-05",
        "2017-06-06",
        "2017-06-07",
        "2017-06-12",
        "2017-06-13",
        "2017-06-14",
        "2017-06-18"
      ]
    },
    {
      "firstName":"Jamie",
      "lastName":"Lohmeier",
      "email":"jlohmeier@hubspotpartners.com",
      "country":"Spain",
      "availableDates":[
        "2017-06-06",
        "2017-06-07",
        "2017-06-09",
        "2017-06-12",
        "2017-06-13",
        "2017-06-14",
        "2017-06-22"
      ]
    },
    {
      "firstName":"Yvette",
      "lastName":"Buegler",
      "email":"ybuegler@hubspotpartners.com",
      "country":"Spain",
      "availableDates":[
        "2017-06-05",
        "2017-06-06",
        "2017-06-07",
        "2017-06-09",
        "2017-06-13",
        "2017-06-14",
        "2017-06-15",
        "2017-06-16",
        "2017-06-17",
        "2017-06-20"
      ]
    },
    {
      "firstName":"Ada",
      "lastName":"Silvestrini",
      "email":"asilvestrini@hubspotpartners.com",
      "country":"Spain",
      "availableDates":[
        "2017-06-06",
        "2017-06-07",
        "2017-06-13",
        "2017-06-14",
        "2017-06-19",
        "2017-06-20"
      ]
    },
    {
      "firstName":"Marcelo",
      "lastName":"Thoene",
      "email":"mthoene@hubspotpartners.com",
      "country":"Spain",
      "availableDates":[
        "2017-06-06",
        "2017-06-07",
        "2017-06-13",
        "2017-06-14",
        "2017-06-16",
        "2017-06-17",
        "2017-06-19",
        "2017-06-20"
      ]
    },
    {
      "firstName":"Yulanda",
      "lastName":"Muckerman",
      "email":"ymuckerman@hubspotpartners.com",
      "country":"Spain",
      "availableDates":[
        "2017-06-10",
        "2017-06-11",
        "2017-06-16",
        "2017-06-17",
        "2017-06-19",
        "2017-06-22",
        "2017-06-24"
      ]
    },
    {
      "firstName":"Jamison",
      "lastName":"Bongio",
      "email":"jbongio@hubspotpartners.com",
      "country":"Spain",
      "availableDates":[
        "2017-06-05",
        "2017-06-09",
        "2017-06-15",
        "2017-06-16"
      ]
    },
    {
      "firstName":"Tova",
      "lastName":"Cremin",
      "email":"tcremin@hubspotpartners.com",
      "country":"Spain",
      "availableDates":[
        "2017-06-04",
        "2017-06-05",
        "2017-06-11",
        "2017-06-12",
        "2017-06-16",
        "2017-06-18",
        "2017-06-19"
      ]
    },
    {
      "firstName":"Jeanie",
      "lastName":"Solverud",
      "email":"jsolverud@hubspotpartners.com",
      "country":"Spain",
      "availableDates":[
        "2017-06-04",
        "2017-06-16"
      ]
    },
    {
      "firstName":"Cherise",
      "lastName":"Bloise",
      "email":"cbloise@hubspotpartners.com",
      "country":"Spain",
      "availableDates":[
        "2017-06-10",
        "2017-06-12",
        "2017-06-16",
        "2017-06-20"
      ]
    },
    {
      "firstName":"Letha",
      "lastName":"Soldner",
      "email":"lsoldner@hubspotpartners.com",
      "country":"Spain",
      "availableDates":[
        "2017-06-04",
        "2017-06-10",
        "2017-06-19",
        "2017-06-20"
      ]
    },
    {
      "firstName":"Inga",
      "lastName":"Brownsword",
      "email":"ibrownsword@hubspotpartners.com",
      "country":"Spain",
      "availableDates":[
        "2017-06-03",
        "2017-06-04",
        "2017-06-05",
        "2017-06-09",
        "2017-06-19",
        "2017-06-20",
        "2017-06-24"
      ]
    },
    {
      "firstName":"Camila",
      "lastName":"Aseng",
      "email":"caseng@hubspotpartners.com",
      "country":"Spain",
      "availableDates":[
        "2017-06-09",
        "2017-06-11",
        "2017-06-12",
        "2017-06-19",
        "2017-06-20"
      ]
    },
    {
      "firstName":"Sol",
      "lastName":"Korenek",
      "email":"skorenek@hubspotpartners.com",
      "country":"Spain",
      "availableDates":[
        "2017-06-05",
        "2017-06-11",
        "2017-06-16",
        "2017-06-20"
      ]
    },
    {
      "firstName":"Cathey",
      "lastName":"Ovalle",
      "email":"covalle@hubspotpartners.com",
      "country":"Spain",
      "availableDates":[
        "2017-06-04",
        "2017-06-09",
        "2017-06-10",
        "2017-06-11",
        "2017-06-12",
        "2017-06-17",
        "2017-06-26"
      ]
    },
    {
      "firstName":"Mellisa",
      "lastName":"Kajder",
      "email":"mkajder@hubspotpartners.com",
      "country":"Mexico",
      "availableDates":[
        "2017-06-17",
        "2017-06-18",
        "2017-06-19",
        "2017-06-20",
        "2017-06-21",
        "2017-06-24",
        "2017-06-26",
        "2017-06-27",
        "2017-06-28",
        "2017-07-03"
      ]
    },
    {
      "firstName":"Vickie",
      "lastName":"Paget",
      "email":"vpaget@hubspotpartners.com",
      "country":"Mexico",
      "availableDates":[
        "2017-06-17",
        "2017-06-18",
        "2017-06-19",
        "2017-06-20",
        "2017-06-28",
        "2017-07-02"
      ]
    },
    {
      "firstName":"Abe",
      "lastName":"Rustad",
      "email":"arustad@hubspotpartners.com",
      "country":"Mexico",
      "availableDates":[
        "2017-06-17",
        "2017-06-18",
        "2017-06-19",
        "2017-06-20",
        "2017-06-26",
        "2017-06-28",
        "2017-06-29",
        "2017-07-02",
        "2017-07-03",
        "2017-07-04",
        "2017-07-08"
      ]
    },
    {
      "firstName":"Chiquita",
      "lastName":"Verfaille",
      "email":"cverfaille@hubspotpartners.com",
      "country":"Mexico",
      "availableDates":[
        "2017-06-17",
        "2017-06-18",
        "2017-06-19",
        "2017-06-20",
        "2017-06-23",
        "2017-06-25",
        "2017-06-27",
        "2017-06-28",
        "2017-07-03"
      ]
    },
    {
      "firstName":"Noel",
      "lastName":"Zadeh",
      "email":"nzadeh@hubspotpartners.com",
      "country":"Mexico",
      "availableDates":[
        "2017-06-17",
        "2017-06-18",
        "2017-06-19",
        "2017-06-20",
        "2017-06-27",
        "2017-06-29",
        "2017-07-02",
        "2017-07-05",
        "2017-07-06"
      ]
    },
    {
      "firstName":"Janeth",
      "lastName":"Dimitriou",
      "email":"jdimitriou@hubspotpartners.com",
      "country":"Mexico",
      "availableDates":[
        "2017-06-17",
        "2017-06-18",
        "2017-06-19",
        "2017-06-20",
        "2017-06-25",
        "2017-06-26",
        "2017-06-29",
        "2017-07-05"
      ]
    },
    {
      "firstName":"Velia",
      "lastName":"Sawyer",
      "email":"vsawyer@hubspotpartners.com",
      "country":"Mexico",
      "availableDates":[
        "2017-06-17",
        "2017-06-18",
        "2017-06-19",
        "2017-06-20",
        "2017-06-26"
      ]
    },
    {
      "firstName":"Kesha",
      "lastName":"Dungey",
      "email":"kdungey@hubspotpartners.com",
      "country":"Mexico",
      "availableDates":[
        "2017-06-17",
        "2017-06-18",
        "2017-06-19",
        "2017-06-20",
        "2017-06-23",
        "2017-06-24",
        "2017-06-25",
        "2017-06-26",
        "2017-06-28",
        "2017-06-29"
      ]
    },
    {
      "firstName":"Telma",
      "lastName":"Higgs",
      "email":"thiggs@hubspotpartners.com",
      "country":"Mexico",
      "availableDates":[
        "2017-06-17",
        "2017-06-18",
        "2017-06-19",
        "2017-06-20",
        "2017-06-21",
        "2017-06-26",
        "2017-06-27",
        "2017-06-28",
        "2017-07-02",
        "2017-07-05"
      ]
    },
    {
      "firstName":"Petra",
      "lastName":"Cordwell",
      "email":"pcordwell@hubspotpartners.com",
      "country":"Mexico",
      "availableDates":[
        "2017-06-17",
        "2017-06-18",
        "2017-06-19",
        "2017-06-20",
        "2017-06-22",
        "2017-06-24",
        "2017-06-30",
        "2017-07-02",
        "2017-07-04",
        "2017-07-05"
      ]
    },
    {
      "firstName":"Korey",
      "lastName":"Coffelt",
      "email":"kcoffelt@hubspotpartners.com",
      "country":"Mexico",
      "availableDates":[
        "2017-06-17",
        "2017-06-18",
        "2017-06-19",
        "2017-06-20",
        "2017-06-24",
        "2017-06-25",
        "2017-06-26",
        "2017-06-27",
        "2017-07-03",
        "2017-07-06"
      ]
    },
    {
      "firstName":"Jolie",
      "lastName":"Loukidis",
      "email":"jloukidis@hubspotpartners.com",
      "country":"Mexico",
      "availableDates":[
        "2017-06-17",
        "2017-06-18",
        "2017-06-19",
        "2017-06-20",
        "2017-06-21",
        "2017-06-22",
        "2017-06-23",
        "2017-06-28",
        "2017-06-29",
        "2017-07-02",
        "2017-07-03",
        "2017-07-05"
      ]
    },
    {
      "firstName":"Fernanda",
      "lastName":"Whippo",
      "email":"fwhippo@hubspotpartners.com",
      "country":"Mexico",
      "availableDates":[
        "2017-06-17",
        "2017-06-18",
        "2017-06-19",
        "2017-06-20",
        "2017-06-29",
        "2017-07-04",
        "2017-07-06"
      ]
    },
    {
      "firstName":"Cleopatra",
      "lastName":"Westerman",
      "email":"cwesterman@hubspotpartners.com",
      "country":"Mexico",
      "availableDates":[
        "2017-06-17",
        "2017-06-18",
        "2017-06-19",
        "2017-06-20",
        "2017-06-21",
        "2017-06-28",
        "2017-07-06",
        "2017-07-10"
      ]
    },
    {
      "firstName":"George",
      "lastName":"Lehneis",
      "email":"glehneis@hubspotpartners.com",
      "country":"Mexico",
      "availableDates":[
        "2017-06-17",
        "2017-06-18",
        "2017-06-19",
        "2017-06-20",
        "2017-06-25",
        "2017-06-27",
        "2017-06-29",
        "2017-07-02",
        "2017-07-03",
        "2017-07-04",
        "2017-07-06"
      ]
    },
    {
      "firstName":"Kathern",
      "lastName":"Tockey",
      "email":"ktockey@hubspotpartners.com",
      "country":"Mexico",
      "availableDates":[
        "2017-06-23",
        "2017-06-24",
        "2017-06-28",
        "2017-07-02",
        "2017-07-05"
      ]
    },
    {
      "firstName":"Shanice",
      "lastName":"Rowell",
      "email":"srowell@hubspotpartners.com",
      "country":"Mexico",
      "availableDates":[
        "2017-06-24",
        "2017-06-25",
        "2017-06-26",
        "2017-06-27",
        "2017-07-04",
        "2017-07-10"
      ]
    },
    {
      "firstName":"Dania",
      "lastName":"Gales",
      "email":"dgales@hubspotpartners.com",
      "country":"Mexico",
      "availableDates":[
        "2017-06-24",
        "2017-06-27",
        "2017-06-29",
        "2017-07-05",
        "2017-07-06"
      ]
    },
    {
      "firstName":"Daniel",
      "lastName":"Elko",
      "email":"delko@hubspotpartners.com",
      "country":"Mexico",
      "availableDates":[
        "2017-06-28",
        "2017-07-06",
        "2017-07-10"
      ]
    },
    {
      "firstName":"Agnus",
      "lastName":"Purkett",
      "email":"apurkett@hubspotpartners.com",
      "country":"Mexico",
      "availableDates":[
        "2017-06-21",
        "2017-06-25",
        "2017-06-26",
        "2017-07-03"
      ]
    },
    {
      "firstName":"Anibal",
      "lastName":"Colclough",
      "email":"acolclough@hubspotpartners.com",
      "country":"Mexico",
      "availableDates":[
        "2017-06-21",
        "2017-06-25",
        "2017-06-28",
        "2017-07-05"
      ]
    },
    {
      "firstName":"Lakeesha",
      "lastName":"Vandenacre",
      "email":"lvandenacre@hubspotpartners.com",
      "country":"Mexico",
      "availableDates":[
        "2017-06-26",
        "2017-06-27",
        "2017-07-05",
        "2017-07-06",
        "2017-07-09"
      ]
    },
    {
      "firstName":"Dortha",
      "lastName":"Lavatch",
      "email":"dlavatch@hubspotpartners.com",
      "country":"Mexico",
      "availableDates":[
        "2017-06-22",
        "2017-06-24",
        "2017-06-25",
        "2017-06-29",
        "2017-07-02",
        "2017-07-05"
      ]
    },
    {
      "firstName":"Jonie",
      "lastName":"Persky",
      "email":"jpersky@hubspotpartners.com",
      "country":"Mexico",
      "availableDates":[
        "2017-06-25",
        "2017-06-26",
        "2017-06-29"
      ]
    },
    {
      "firstName":"Brandon",
      "lastName":"Bonesteel",
      "email":"bbonesteel@hubspotpartners.com",
      "country":"Mexico",
      "availableDates":[
        "2017-06-22",
        "2017-06-30",
        "2017-07-06"
      ]
    },
    {
      "firstName":"Stacey",
      "lastName":"Medel",
      "email":"smedel@hubspotpartners.com",
      "country":"Canada",
      "availableDates":[
        "2017-06-13",
        "2017-06-14",
        "2017-06-19",
        "2017-06-20",
        "2017-06-24",
        "2017-06-26",
        "2017-06-27",
        "2017-07-01",
        "2017-07-02"
      ]
    },
    {
      "firstName":"Jeannette",
      "lastName":"Scavetta",
      "email":"jscavetta@hubspotpartners.com",
      "country":"Canada",
      "availableDates":[
        "2017-06-13",
        "2017-06-14",
        "2017-06-19",
        "2017-06-20",
        "2017-06-23",
        "2017-06-25",
        "2017-06-27",
        "2017-06-30",
        "2017-07-01",
        "2017-07-02"
      ]
    },
    {
      "firstName":"Cruz",
      "lastName":"Glass",
      "email":"cglass@hubspotpartners.com",
      "country":"Canada",
      "availableDates":[
        "2017-06-13",
        "2017-06-14",
        "2017-06-25",
        "2017-06-26",
        "2017-06-27",
        "2017-06-30",
        "2017-07-01",
        "2017-07-02"
      ]
    },
    {
      "firstName":"Lucienne",
      "lastName":"Chiappone",
      "email":"lchiappone@hubspotpartners.com",
      "country":"Canada",
      "availableDates":[
        "2017-06-13",
        "2017-06-14",
        "2017-06-17",
        "2017-06-24",
        "2017-06-26",
        "2017-06-27",
        "2017-06-30",
        "2017-07-01",
        "2017-07-02"
      ]
    },
    {
      "firstName":"Reda",
      "lastName":"Lirag",
      "email":"rlirag@hubspotpartners.com",
      "country":"Canada",
      "availableDates":[
        "2017-06-13",
        "2017-06-14",
        "2017-06-19",
        "2017-06-20",
        "2017-06-21",
        "2017-06-27",
        "2017-07-01",
        "2017-07-02",
        "2017-07-05"
      ]
    },
    {
      "firstName":"Maple",
      "lastName":"Kolesnik",
      "email":"mkolesnik@hubspotpartners.com",
      "country":"Canada",
      "availableDates":[
        "2017-06-13",
        "2017-06-14",
        "2017-06-17",
        "2017-06-20",
        "2017-07-01",
        "2017-07-02"
      ]
    },
    {
      "firstName":"Lani",
      "lastName":"Olive",
      "email":"lolive@hubspotpartners.com",
      "country":"Canada",
      "availableDates":[
        "2017-06-13",
        "2017-06-14",
        "2017-06-27",
        "2017-06-30",
        "2017-07-01",
        "2017-07-02"
      ]
    },
    {
      "firstName":"Isaura",
      "lastName":"Thrailkill",
      "email":"ithrailkill@hubspotpartners.com",
      "country":"Canada",
      "availableDates":[
        "2017-06-13",
        "2017-06-14",
        "2017-06-20",
        "2017-06-30",
        "2017-07-01",
        "2017-07-02"
      ]
    },
    {
      "firstName":"Shante",
      "lastName":"Trudillo",
      "email":"strudillo@hubspotpartners.com",
      "country":"Canada",
      "availableDates":[
        "2017-06-13",
        "2017-06-14",
        "2017-06-18",
        "2017-06-26",
        "2017-06-28",
        "2017-07-01",
        "2017-07-02"
      ]
    },
    {
      "firstName":"Asley",
      "lastName":"Wiederstein",
      "email":"awiederstein@hubspotpartners.com",
      "country":"Canada",
      "availableDates":[
        "2017-06-13",
        "2017-06-14",
        "2017-06-18",
        "2017-06-24",
        "2017-06-25",
        "2017-06-26",
        "2017-06-30",
        "2017-07-01",
        "2017-07-02"
      ]
    },
    {
      "firstName":"Johnie",
      "lastName":"Ghea",
      "email":"jghea@hubspotpartners.com",
      "country":"Canada",
      "availableDates":[
        "2017-06-13",
        "2017-06-14",
        "2017-06-17",
        "2017-06-20",
        "2017-06-24",
        "2017-06-29",
        "2017-06-30",
        "2017-07-01",
        "2017-07-02",
        "2017-07-06"
      ]
    },
    {
      "firstName":"Iesha",
      "lastName":"Kittredge",
      "email":"ikittredge@hubspotpartners.com",
      "country":"Canada",
      "availableDates":[
        "2017-06-13",
        "2017-06-14",
        "2017-06-17",
        "2017-06-18",
        "2017-06-19",
        "2017-06-29",
        "2017-07-01",
        "2017-07-02"
      ]
    },
    {
      "firstName":"Pattie",
      "lastName":"Meloche",
      "email":"pmeloche@hubspotpartners.com",
      "country":"Canada",
      "availableDates":[
        "2017-06-13",
        "2017-06-14",
        "2017-06-18",
        "2017-06-24",
        "2017-06-27",
        "2017-07-01",
        "2017-07-02"
      ]
    },
    {
      "firstName":"Jonah",
      "lastName":"Dooms",
      "email":"jdooms@hubspotpartners.com",
      "country":"Canada",
      "availableDates":[
        "2017-06-13",
        "2017-06-14",
        "2017-06-17",
        "2017-06-27",
        "2017-07-01",
        "2017-07-02"
      ]
    },
    {
      "firstName":"Louisa",
      "lastName":"Wims",
      "email":"lwims@hubspotpartners.com",
      "country":"Canada",
      "availableDates":[
        "2017-06-13",
        "2017-06-14",
        "2017-06-19",
        "2017-07-01",
        "2017-07-02"
      ]
    },
    {
      "firstName":"Kathlyn",
      "lastName":"Stampka",
      "email":"kstampka@hubspotpartners.com",
      "country":"Canada",
      "availableDates":[
        "2017-06-17",
        "2017-06-18",
        "2017-06-19",
        "2017-06-23",
        "2017-06-27",
        "2017-07-05"
      ]
    },
    {
      "firstName":"Rose",
      "lastName":"Viernes",
      "email":"rviernes@hubspotpartners.com",
      "country":"Canada",
      "availableDates":[
        "2017-06-19",
        "2017-06-20",
        "2017-06-26",
        "2017-06-27",
        "2017-06-30"
      ]
    },
    {
      "firstName":"Harrison",
      "lastName":"Ebilane",
      "email":"hebilane@hubspotpartners.com",
      "country":"Canada",
      "availableDates":[
        "2017-06-17",
        "2017-06-18",
        "2017-07-04"
      ]
    },
    {
      "firstName":"Willy",
      "lastName":"Mateos",
      "email":"wmateos@hubspotpartners.com",
      "country":"Canada",
      "availableDates":[
        "2017-06-25",
        "2017-06-30"
      ]
    },
    {
      "firstName":"Margot",
      "lastName":"Stangroom",
      "email":"mstangroom@hubspotpartners.com",
      "country":"Canada",
      "availableDates":[
        "2017-06-19",
        "2017-06-26",
        "2017-06-27",
        "2017-06-29"
      ]
    },
    {
      "firstName":"Coralee",
      "lastName":"Scudder",
      "email":"cscudder@hubspotpartners.com",
      "country":"Canada",
      "availableDates":[
        "2017-06-19",
        "2017-06-21",
        "2017-06-29"
      ]
    },
    {
      "firstName":"Trish",
      "lastName":"Repsher",
      "email":"trepsher@hubspotpartners.com",
      "country":"Canada",
      "availableDates":[
        "2017-06-24",
        "2017-06-27",
        "2017-06-30"
      ]
    },
    {
      "firstName":"Dayle",
      "lastName":"Thi",
      "email":"dthi@hubspotpartners.com",
      "country":"Canada",
      "availableDates":[
        "2017-06-19",
        "2017-06-20",
        "2017-06-21",
        "2017-06-23",
        "2017-06-29",
        "2017-06-30"
      ]
    },
    {
      "firstName":"Arnita",
      "lastName":"Dresher",
      "email":"adresher@hubspotpartners.com",
      "country":"Canada",
      "availableDates":[
        "2017-06-16",
        "2017-06-18",
        "2017-06-19",
        "2017-06-30"
      ]
    },
    {
      "firstName":"Pam",
      "lastName":"Pelkey",
      "email":"ppelkey@hubspotpartners.com",
      "country":"Canada",
      "availableDates":[
        "2017-06-18",
        "2017-06-20",
        "2017-06-24",
        "2017-06-27",
        "2017-06-30",
        "2017-07-04"
      ]
    },
    {
      "firstName":"Providencia",
      "lastName":"Torrens",
      "email":"ptorrens@hubspotpartners.com",
      "country":"Singapore",
      "availableDates":[
        "2017-05-24",
        "2017-05-30",
        "2017-05-31",
        "2017-06-01",
        "2017-06-02",
        "2017-06-09",
        "2017-06-15"
      ]
    },
    {
      "firstName":"Rene",
      "lastName":"Rackett",
      "email":"rrackett@hubspotpartners.com",
      "country":"Singapore",
      "availableDates":[
        "2017-05-24",
        "2017-05-25",
        "2017-05-28",
        "2017-05-30",
        "2017-05-31",
        "2017-06-01",
        "2017-06-02",
        "2017-06-05",
        "2017-06-08",
        "2017-06-13"
      ]
    },
    {
      "firstName":"Susanna",
      "lastName":"Wilkens",
      "email":"swilkens@hubspotpartners.com",
      "country":"Singapore",
      "availableDates":[
        "2017-05-23",
        "2017-05-25",
        "2017-05-28",
        "2017-05-30",
        "2017-05-31",
        "2017-06-01",
        "2017-06-02",
        "2017-06-09"
      ]
    },
    {
      "firstName":"Willard",
      "lastName":"Reisner",
      "email":"wreisner@hubspotpartners.com",
      "country":"Singapore",
      "availableDates":[
        "2017-05-23",
        "2017-05-24",
        "2017-05-27",
        "2017-05-29",
        "2017-05-30",
        "2017-05-31",
        "2017-06-01",
        "2017-06-02",
        "2017-06-05",
        "2017-06-10"
      ]
    },
    {
      "firstName":"Katelin",
      "lastName":"Haarstad",
      "email":"khaarstad@hubspotpartners.com",
      "country":"Singapore",
      "availableDates":[
        "2017-05-24",
        "2017-05-30",
        "2017-05-31",
        "2017-06-01",
        "2017-06-02",
        "2017-06-05"
      ]
    },
    {
      "firstName":"Tomika",
      "lastName":"Bartman",
      "email":"tbartman@hubspotpartners.com",
      "country":"Singapore",
      "availableDates":[
        "2017-05-25",
        "2017-05-29",
        "2017-05-30",
        "2017-05-31",
        "2017-06-01",
        "2017-06-02",
        "2017-06-05",
        "2017-06-10"
      ]
    },
    {
      "firstName":"Lucretia",
      "lastName":"Rocquemore",
      "email":"lrocquemore@hubspotpartners.com",
      "country":"Singapore",
      "availableDates":[
        "2017-05-23",
        "2017-05-24",
        "2017-05-30",
        "2017-05-31",
        "2017-06-01",
        "2017-06-02"
      ]
    },
    {
      "firstName":"Torrie",
      "lastName":"Mooers",
      "email":"tmooers@hubspotpartners.com",
      "country":"Singapore",
      "availableDates":[
        "2017-05-23",
        "2017-05-24",
        "2017-05-28",
        "2017-05-29",
        "2017-05-30",
        "2017-05-31",
        "2017-06-01",
        "2017-06-02",
        "2017-06-05",
        "2017-06-09"
      ]
    },
    {
      "firstName":"Aaron",
      "lastName":"Durdy",
      "email":"adurdy@hubspotpartners.com",
      "country":"Singapore",
      "availableDates":[
        "2017-05-23",
        "2017-05-28",
        "2017-05-30",
        "2017-05-31",
        "2017-06-01",
        "2017-06-02",
        "2017-06-03"
      ]
    },
    {
      "firstName":"Pete",
      "lastName":"Sasso",
      "email":"psasso@hubspotpartners.com",
      "country":"Singapore",
      "availableDates":[
        "2017-05-27",
        "2017-05-30",
        "2017-05-31",
        "2017-06-01",
        "2017-06-02"
      ]
    },
    {
      "firstName":"Sheba",
      "lastName":"Charfauros",
      "email":"scharfauros@hubspotpartners.com",
      "country":"Singapore",
      "availableDates":[
        "2017-05-30",
        "2017-05-31",
        "2017-06-01",
        "2017-06-02",
        "2017-06-09",
        "2017-06-14"
      ]
    },
    {
      "firstName":"Pat",
      "lastName":"Bushovisky",
      "email":"pbushovisky@hubspotpartners.com",
      "country":"Singapore",
      "availableDates":[
        "2017-05-27",
        "2017-05-28",
        "2017-05-30",
        "2017-05-31",
        "2017-06-01",
        "2017-06-02",
        "2017-06-04",
        "2017-06-05",
        "2017-06-06",
        "2017-06-10"
      ]
    },
    {
      "firstName":"Lavonia",
      "lastName":"Lamphiear",
      "email":"llamphiear@hubspotpartners.com",
      "country":"Singapore",
      "availableDates":[
        "2017-05-23",
        "2017-05-24",
        "2017-05-25",
        "2017-05-30",
        "2017-05-31",
        "2017-06-01",
        "2017-06-02",
        "2017-06-08"
      ]
    },
    {
      "firstName":"Roxane",
      "lastName":"Ojeda",
      "email":"rojeda@hubspotpartners.com",
      "country":"Singapore",
      "availableDates":[
        "2017-05-24",
        "2017-05-29",
        "2017-05-30",
        "2017-05-31",
        "2017-06-01",
        "2017-06-02"
      ]
    },
    {
      "firstName":"Sherill",
      "lastName":"Petrina",
      "email":"spetrina@hubspotpartners.com",
      "country":"Singapore",
      "availableDates":[
        "2017-05-26",
        "2017-05-27",
        "2017-05-28",
        "2017-05-30",
        "2017-05-31",
        "2017-06-01",
        "2017-06-02",
        "2017-06-05"
      ]
    },
    {
      "firstName":"Clora",
      "lastName":"Rechtzigel",
      "email":"crechtzigel@hubspotpartners.com",
      "country":"Singapore",
      "availableDates":[
        "2017-05-23",
        "2017-05-24",
        "2017-05-25",
        "2017-05-28",
        "2017-06-04",
        "2017-06-14"
      ]
    },
    {
      "firstName":"Francene",
      "lastName":"Opdahl",
      "email":"fopdahl@hubspotpartners.com",
      "country":"Singapore",
      "availableDates":[
        "2017-05-26",
        "2017-05-28",
        "2017-05-29",
        "2017-06-03",
        "2017-06-05"
      ]
    },
    {
      "firstName":"Alyssa",
      "lastName":"Hovanec",
      "email":"ahovanec@hubspotpartners.com",
      "country":"Singapore",
      "availableDates":[
        "2017-06-05",
        "2017-06-06",
        "2017-06-09",
        "2017-06-10"
      ]
    },
    {
      "firstName":"Steven",
      "lastName":"Duwhite",
      "email":"sduwhite@hubspotpartners.com",
      "country":"Singapore",
      "availableDates":[
        "2017-05-26",
        "2017-05-27",
        "2017-05-28",
        "2017-05-29",
        "2017-06-05",
        "2017-06-10",
        "2017-06-14"
      ]
    },
    {
      "firstName":"Romaine",
      "lastName":"Pegg",
      "email":"rpegg@hubspotpartners.com",
      "country":"Singapore",
      "availableDates":[
        "2017-05-24",
        "2017-05-27",
        "2017-05-28",
        "2017-06-06",
        "2017-06-08",
        "2017-06-14"
      ]
    },
    {
      "firstName":"Sharmaine",
      "lastName":"Stenquist",
      "email":"sstenquist@hubspotpartners.com",
      "country":"Singapore",
      "availableDates":[
        "2017-05-26",
        "2017-05-27",
        "2017-05-28",
        "2017-06-04",
        "2017-06-05",
        "2017-06-06",
        "2017-06-10"
      ]
    },
    {
      "firstName":"Larae",
      "lastName":"Rassmussen",
      "email":"lrassmussen@hubspotpartners.com",
      "country":"Singapore",
      "availableDates":[
        "2017-05-23",
        "2017-05-24",
        "2017-05-29",
        "2017-06-09"
      ]
    },
    {
      "firstName":"Jannie",
      "lastName":"Bittick",
      "email":"jbittick@hubspotpartners.com",
      "country":"Singapore",
      "availableDates":[
        "2017-05-28",
        "2017-05-29",
        "2017-06-05",
        "2017-06-10"
      ]
    },
    {
      "firstName":"Christen",
      "lastName":"Melott",
      "email":"cmelott@hubspotpartners.com",
      "country":"Singapore",
      "availableDates":[
        "2017-05-28",
        "2017-06-04",
        "2017-06-09"
      ]
    },
    {
      "firstName":"Mireya",
      "lastName":"Fickett",
      "email":"mfickett@hubspotpartners.com",
      "country":"Singapore",
      "availableDates":[
        "2017-05-23",
        "2017-05-27",
        "2017-05-29"
      ]
    },
    {
      "firstName":"Katie",
      "lastName":"Mruk",
      "email":"kmruk@hubspotpartners.com",
      "country":"Japan",
      "availableDates":[
        "2017-06-13",
        "2017-06-15",
        "2017-06-17",
        "2017-06-18",
        "2017-06-30",
        "2017-07-01"
      ]
    },
    {
      "firstName":"Vivienne",
      "lastName":"Frett",
      "email":"vfrett@hubspotpartners.com",
      "country":"Japan",
      "availableDates":[
        "2017-06-14",
        "2017-06-17",
        "2017-06-18",
        "2017-06-24",
        "2017-06-30",
        "2017-07-01"
      ]
    },
    {
      "firstName":"Cinda",
      "lastName":"Dajani",
      "email":"cdajani@hubspotpartners.com",
      "country":"Japan",
      "availableDates":[
        "2017-06-14",
        "2017-06-17",
        "2017-06-18",
        "2017-06-28",
        "2017-06-29",
        "2017-06-30",
        "2017-07-01",
        "2017-07-02",
        "2017-07-06"
      ]
    },
    {
      "firstName":"Chris",
      "lastName":"Balter",
      "email":"cbalter@hubspotpartners.com",
      "country":"Japan",
      "availableDates":[
        "2017-06-14",
        "2017-06-15",
        "2017-06-17",
        "2017-06-18",
        "2017-06-27",
        "2017-06-28",
        "2017-06-30",
        "2017-07-01"
      ]
    },
    {
      "firstName":"Seema",
      "lastName":"Gasbarro",
      "email":"sgasbarro@hubspotpartners.com",
      "country":"Japan",
      "availableDates":[
        "2017-06-15",
        "2017-06-17",
        "2017-06-18",
        "2017-06-30",
        "2017-07-01"
      ]
    },
    {
      "firstName":"Judith",
      "lastName":"Missler",
      "email":"jmissler@hubspotpartners.com",
      "country":"Japan",
      "availableDates":[
        "2017-06-15",
        "2017-06-17",
        "2017-06-18",
        "2017-06-20",
        "2017-06-24",
        "2017-06-30",
        "2017-07-01"
      ]
    },
    {
      "firstName":"Cora",
      "lastName":"Pickert",
      "email":"cpickert@hubspotpartners.com",
      "country":"Japan",
      "availableDates":[
        "2017-06-15",
        "2017-06-17",
        "2017-06-18",
        "2017-06-25",
        "2017-06-26",
        "2017-06-27",
        "2017-06-30",
        "2017-07-01",
        "2017-07-06"
      ]
    },
    {
      "firstName":"Conchita",
      "lastName":"Sudan",
      "email":"csudan@hubspotpartners.com",
      "country":"Japan",
      "availableDates":[
        "2017-06-15",
        "2017-06-17",
        "2017-06-18",
        "2017-06-27",
        "2017-06-30",
        "2017-07-01"
      ]
    },
    {
      "firstName":"Malcolm",
      "lastName":"Streifel",
      "email":"mstreifel@hubspotpartners.com",
      "country":"Japan",
      "availableDates":[
        "2017-06-16",
        "2017-06-17",
        "2017-06-18",
        "2017-06-22",
        "2017-06-26",
        "2017-06-27",
        "2017-06-28",
        "2017-06-30",
        "2017-07-01"
      ]
    },
    {
      "firstName":"Melinda",
      "lastName":"Vandel",
      "email":"mvandel@hubspotpartners.com",
      "country":"Japan",
      "availableDates":[
        "2017-06-17",
        "2017-06-18",
        "2017-06-21",
        "2017-06-24",
        "2017-06-26",
        "2017-06-28",
        "2017-06-30",
        "2017-07-01"
      ]
    },
    {
      "firstName":"Kasandra",
      "lastName":"Nervis",
      "email":"knervis@hubspotpartners.com",
      "country":"Japan",
      "availableDates":[
        "2017-06-13",
        "2017-06-15",
        "2017-06-16",
        "2017-06-17",
        "2017-06-18",
        "2017-06-27",
        "2017-06-28",
        "2017-06-30",
        "2017-07-01",
        "2017-07-02"
      ]
    },
    {
      "firstName":"Elenora",
      "lastName":"Beyal",
      "email":"ebeyal@hubspotpartners.com",
      "country":"Japan",
      "availableDates":[
        "2017-06-15",
        "2017-06-16",
        "2017-06-17",
        "2017-06-18",
        "2017-06-20",
        "2017-06-23",
        "2017-06-24",
        "2017-06-26",
        "2017-06-29",
        "2017-06-30",
        "2017-07-01"
      ]
    },
    {
      "firstName":"Naida",
      "lastName":"Mccaman",
      "email":"nmccaman@hubspotpartners.com",
      "country":"Japan",
      "availableDates":[
        "2017-06-17",
        "2017-06-18",
        "2017-06-21",
        "2017-06-29",
        "2017-06-30",
        "2017-07-01",
        "2017-07-02"
      ]
    },
    {
      "firstName":"Noel",
      "lastName":"Brick",
      "email":"nbrick@hubspotpartners.com",
      "country":"Japan",
      "availableDates":[
        "2017-06-16",
        "2017-06-17",
        "2017-06-18",
        "2017-06-26",
        "2017-06-30",
        "2017-07-01",
        "2017-07-02"
      ]
    },
    {
      "firstName":"Jacqulyn",
      "lastName":"Ditore",
      "email":"jditore@hubspotpartners.com",
      "country":"Japan",
      "availableDates":[
        "2017-06-17",
        "2017-06-18",
        "2017-06-21",
        "2017-06-26",
        "2017-06-30",
        "2017-07-01"
      ]
    },
    {
      "firstName":"Alphonse",
      "lastName":"Drobot",
      "email":"adrobot@hubspotpartners.com",
      "country":"Japan",
      "availableDates":[
        "2017-06-14",
        "2017-06-16",
        "2017-06-17",
        "2017-06-18",
        "2017-06-26",
        "2017-06-30",
        "2017-07-01"
      ]
    },
    {
      "firstName":"Simon",
      "lastName":"Lanclos",
      "email":"slanclos@hubspotpartners.com",
      "country":"Japan",
      "availableDates":[
        "2017-06-13",
        "2017-06-22",
        "2017-06-26",
        "2017-06-28",
        "2017-07-02"
      ]
    },
    {
      "firstName":"Carolynn",
      "lastName":"Gebhardt",
      "email":"cgebhardt@hubspotpartners.com",
      "country":"Japan",
      "availableDates":[
        "2017-06-15",
        "2017-06-16",
        "2017-06-24",
        "2017-06-28",
        "2017-06-29",
        "2017-07-04"
      ]
    },
    {
      "firstName":"Christel",
      "lastName":"Oney",
      "email":"coney@hubspotpartners.com",
      "country":"Japan",
      "availableDates":[
        "2017-06-15",
        "2017-06-21",
        "2017-06-22",
        "2017-06-24",
        "2017-06-25",
        "2017-06-27",
        "2017-06-28",
        "2017-07-02"
      ]
    },
    {
      "firstName":"Livia",
      "lastName":"Machin",
      "email":"lmachin@hubspotpartners.com",
      "country":"Japan",
      "availableDates":[
        "2017-06-26",
        "2017-06-27",
        "2017-06-28",
        "2017-06-29",
        "2017-07-05"
      ]
    },
    {
      "firstName":"Gabriela",
      "lastName":"Impson",
      "email":"gimpson@hubspotpartners.com",
      "country":"Japan",
      "availableDates":[
        "2017-06-15",
        "2017-06-22",
        "2017-06-28",
        "2017-07-04",
        "2017-07-06"
      ]
    },
    {
      "firstName":"Pamelia",
      "lastName":"Regester",
      "email":"pregester@hubspotpartners.com",
      "country":"Japan",
      "availableDates":[
        "2017-06-15",
        "2017-06-16",
        "2017-06-28",
        "2017-07-02"
      ]
    },
    {
      "firstName":"Jacquline",
      "lastName":"Lauth",
      "email":"jlauth@hubspotpartners.com",
      "country":"Japan",
      "availableDates":[
        "2017-06-15",
        "2017-06-22",
        "2017-06-24",
        "2017-06-28",
        "2017-06-29",
        "2017-07-02"
      ]
    },
    {
      "firstName":"Manda",
      "lastName":"Ibanez",
      "email":"mibanez@hubspotpartners.com",
      "country":"Japan",
      "availableDates":[
        "2017-06-14",
        "2017-06-21",
        "2017-06-22",
        "2017-06-28",
        "2017-07-02"
      ]
    },
    {
      "firstName":"Kelle",
      "lastName":"Paugh",
      "email":"kpaugh@hubspotpartners.com",
      "country":"Japan",
      "availableDates":[
        "2017-06-13",
        "2017-06-14",
        "2017-06-21",
        "2017-06-27",
        "2017-07-02"
      ]
    },
    {
      "firstName":"Jefferey",
      "lastName":"Hehl",
      "email":"jhehl@hubspotpartners.com",
      "country":"Japan",
      "availableDates":[
        "2017-06-21",
        "2017-06-24",
        "2017-06-27",
        "2017-06-29"
      ]
    },
    {
      "firstName":"Marivel",
      "lastName":"Wolfinger",
      "email":"mwolfinger@hubspotpartners.com",
      "country":"United Kingdom",
      "availableDates":[
        "2017-05-23",
        "2017-05-24",
        "2017-05-25",
        "2017-05-31",
        "2017-06-01",
        "2017-06-06",
        "2017-06-07",
        "2017-06-08",
        "2017-06-13"
      ]
    },
    {
      "firstName":"Hilma",
      "lastName":"Darsi",
      "email":"hdarsi@hubspotpartners.com",
      "country":"United Kingdom",
      "availableDates":[
        "2017-05-25",
        "2017-05-28",
        "2017-05-30",
        "2017-05-31",
        "2017-06-01",
        "2017-06-04",
        "2017-06-06",
        "2017-06-07",
        "2017-06-08",
        "2017-06-13"
      ]
    },
    {
      "firstName":"Margarett",
      "lastName":"Nini",
      "email":"mnini@hubspotpartners.com",
      "country":"United Kingdom",
      "availableDates":[
        "2017-05-25",
        "2017-05-28",
        "2017-05-31",
        "2017-06-01",
        "2017-06-05",
        "2017-06-06",
        "2017-06-07",
        "2017-06-08"
      ]
    },
    {
      "firstName":"Alphonse",
      "lastName":"Feola",
      "email":"afeola@hubspotpartners.com",
      "country":"United Kingdom",
      "availableDates":[
        "2017-05-22",
        "2017-05-23",
        "2017-05-30",
        "2017-05-31",
        "2017-06-01",
        "2017-06-04",
        "2017-06-05",
        "2017-06-06",
        "2017-06-07",
        "2017-06-14"
      ]
    },
    {
      "firstName":"Torrie",
      "lastName":"Cangey",
      "email":"tcangey@hubspotpartners.com",
      "country":"United Kingdom",
      "availableDates":[
        "2017-05-23",
        "2017-05-31",
        "2017-06-01",
        "2017-06-04",
        "2017-06-05",
        "2017-06-06",
        "2017-06-07"
      ]
    },
    {
      "firstName":"Austin",
      "lastName":"Osterhouse",
      "email":"aosterhouse@hubspotpartners.com",
      "country":"United Kingdom",
      "availableDates":[
        "2017-05-28",
        "2017-05-30",
        "2017-05-31",
        "2017-06-01",
        "2017-06-02",
        "2017-06-06",
        "2017-06-07",
        "2017-06-08",
        "2017-06-09"
      ]
    },
    {
      "firstName":"Johnny",
      "lastName":"Rondon",
      "email":"jrondon@hubspotpartners.com",
      "country":"United Kingdom",
      "availableDates":[
        "2017-05-28",
        "2017-05-31",
        "2017-06-01",
        "2017-06-02",
        "2017-06-03",
        "2017-06-06",
        "2017-06-07"
      ]
    },
    {
      "firstName":"Evangelina",
      "lastName":"Moskos",
      "email":"emoskos@hubspotpartners.com",
      "country":"United Kingdom",
      "availableDates":[
        "2017-05-26",
        "2017-05-28",
        "2017-05-30",
        "2017-05-31",
        "2017-06-01",
        "2017-06-06",
        "2017-06-07"
      ]
    },
    {
      "firstName":"Magaly",
      "lastName":"Godbold",
      "email":"mgodbold@hubspotpartners.com",
      "country":"United Kingdom",
      "availableDates":[
        "2017-05-23",
        "2017-05-31",
        "2017-06-01",
        "2017-06-06",
        "2017-06-07"
      ]
    },
    {
      "firstName":"Eugenie",
      "lastName":"Streat",
      "email":"estreat@hubspotpartners.com",
      "country":"United Kingdom",
      "availableDates":[
        "2017-05-25",
        "2017-05-28",
        "2017-05-30",
        "2017-05-31",
        "2017-06-01",
        "2017-06-02",
        "2017-06-03",
        "2017-06-04",
        "2017-06-05",
        "2017-06-06",
        "2017-06-07",
        "2017-06-08"
      ]
    },
    {
      "firstName":"Laine",
      "lastName":"Zerhusen",
      "email":"lzerhusen@hubspotpartners.com",
      "country":"United Kingdom",
      "availableDates":[
        "2017-05-23",
        "2017-05-25",
        "2017-05-30",
        "2017-05-31",
        "2017-06-01",
        "2017-06-02",
        "2017-06-03",
        "2017-06-06",
        "2017-06-07"
      ]
    },
    {
      "firstName":"Latisha",
      "lastName":"Gaye",
      "email":"lgaye@hubspotpartners.com",
      "country":"United Kingdom",
      "availableDates":[
        "2017-05-25",
        "2017-05-28",
        "2017-05-31",
        "2017-06-01",
        "2017-06-02",
        "2017-06-03",
        "2017-06-06",
        "2017-06-07",
        "2017-06-08"
      ]
    },
    {
      "firstName":"Georgette",
      "lastName":"Marsalis",
      "email":"gmarsalis@hubspotpartners.com",
      "country":"United Kingdom",
      "availableDates":[
        "2017-05-25",
        "2017-05-30",
        "2017-05-31",
        "2017-06-01",
        "2017-06-05",
        "2017-06-06",
        "2017-06-07",
        "2017-06-08"
      ]
    },
    {
      "firstName":"Sharika",
      "lastName":"Vereen",
      "email":"svereen@hubspotpartners.com",
      "country":"United Kingdom",
      "availableDates":[
        "2017-05-23",
        "2017-05-28",
        "2017-05-30",
        "2017-05-31",
        "2017-06-01",
        "2017-06-03",
        "2017-06-06",
        "2017-06-07"
      ]
    },
    {
      "firstName":"Keitha",
      "lastName":"Khoun",
      "email":"kkhoun@hubspotpartners.com",
      "country":"United Kingdom",
      "availableDates":[
        "2017-05-31",
        "2017-06-01",
        "2017-06-02",
        "2017-06-06",
        "2017-06-07"
      ]
    },
    {
      "firstName":"Billye",
      "lastName":"Mrozoski",
      "email":"bmrozoski@hubspotpartners.com",
      "country":"United Kingdom",
      "availableDates":[
        "2017-05-23",
        "2017-05-25",
        "2017-05-26",
        "2017-05-30",
        "2017-05-31",
        "2017-06-01",
        "2017-06-03",
        "2017-06-05",
        "2017-06-06",
        "2017-06-07"
      ]
    },
    {
      "firstName":"Belen",
      "lastName":"Foddrill",
      "email":"bfoddrill@hubspotpartners.com",
      "country":"United Kingdom",
      "availableDates":[
        "2017-05-25",
        "2017-05-27",
        "2017-05-30",
        "2017-06-02",
        "2017-06-04",
        "2017-06-08"
      ]
    },
    {
      "firstName":"Ina",
      "lastName":"Ruocco",
      "email":"iruocco@hubspotpartners.com",
      "country":"United Kingdom",
      "availableDates":[
        "2017-05-25",
        "2017-06-02",
        "2017-06-04",
        "2017-06-08"
      ]
    },
    {
      "firstName":"Dominic",
      "lastName":"Montesinos",
      "email":"dmontesinos@hubspotpartners.com",
      "country":"United Kingdom",
      "availableDates":[
        "2017-05-22",
        "2017-05-26",
        "2017-06-03",
        "2017-06-04",
        "2017-06-14"
      ]
    },
    {
      "firstName":"Noelia",
      "lastName":"Shanaa",
      "email":"nshanaa@hubspotpartners.com",
      "country":"United Kingdom",
      "availableDates":[
        "2017-05-25",
        "2017-06-02",
        "2017-06-05"
      ]
    },
    {
      "firstName":"Percy",
      "lastName":"Roseth",
      "email":"proseth@hubspotpartners.com",
      "country":"United Kingdom",
      "availableDates":[
        "2017-05-27",
        "2017-05-30",
        "2017-06-04",
        "2017-06-09"
      ]
    },
    {
      "firstName":"Joey",
      "lastName":"Grajales",
      "email":"jgrajales@hubspotpartners.com",
      "country":"United Kingdom",
      "availableDates":[
        "2017-06-02",
        "2017-06-04"
      ]
    },
    {
      "firstName":"Cletus",
      "lastName":"Ristow",
      "email":"cristow@hubspotpartners.com",
      "country":"United Kingdom",
      "availableDates":[
        "2017-05-23"
      ]
    },
    {
      "firstName":"Antone",
      "lastName":"Gallups",
      "email":"agallups@hubspotpartners.com",
      "country":"United Kingdom",
      "availableDates":[
        "2017-05-23",
        "2017-05-27",
        "2017-05-30",
        "2017-06-02",
        "2017-06-03",
        "2017-06-04"
      ]
    },
    {
      "firstName":"Francene",
      "lastName":"Raatz",
      "email":"fraatz@hubspotpartners.com",
      "country":"United Kingdom",
      "availableDates":[
        "2017-06-03",
        "2017-06-08",
        "2017-06-11"
      ]
    },
    {
      "firstName":"Chastity",
      "lastName":"Ureno",
      "email":"cureno@hubspotpartners.com",
      "country":"United Kingdom",
      "availableDates":[
        "2017-05-28",
        "2017-05-30",
        "2017-06-03",
        "2017-06-08",
        "2017-06-14"
      ]
    },
    {
      "firstName":"Kimi",
      "lastName":"Guzzardo",
      "email":"kguzzardo@hubspotpartners.com",
      "country":"France",
      "availableDates":[
        "2017-06-12",
        "2017-06-16",
        "2017-06-17",
        "2017-06-18",
        "2017-06-21",
        "2017-06-22",
        "2017-06-23",
        "2017-06-24",
        "2017-06-28"
      ]
    },
    {
      "firstName":"Jessie",
      "lastName":"Swiggum",
      "email":"jswiggum@hubspotpartners.com",
      "country":"France",
      "availableDates":[
        "2017-06-05",
        "2017-06-06",
        "2017-06-14",
        "2017-06-16",
        "2017-06-17",
        "2017-06-21",
        "2017-06-22",
        "2017-06-23",
        "2017-06-24",
        "2017-06-28"
      ]
    },
    {
      "firstName":"Cindy",
      "lastName":"Kinney",
      "email":"ckinney@hubspotpartners.com",
      "country":"France",
      "availableDates":[
        "2017-06-06",
        "2017-06-09",
        "2017-06-14",
        "2017-06-16",
        "2017-06-17",
        "2017-06-22",
        "2017-06-23",
        "2017-06-24",
        "2017-06-27",
        "2017-06-28"
      ]
    },
    {
      "firstName":"Latonia",
      "lastName":"Cooner",
      "email":"lcooner@hubspotpartners.com",
      "country":"France",
      "availableDates":[
        "2017-06-05",
        "2017-06-07",
        "2017-06-16",
        "2017-06-17",
        "2017-06-23",
        "2017-06-24",
        "2017-06-26",
        "2017-06-28"
      ]
    },
    {
      "firstName":"Christiane",
      "lastName":"Hapgood",
      "email":"chapgood@hubspotpartners.com",
      "country":"France",
      "availableDates":[
        "2017-06-05",
        "2017-06-06",
        "2017-06-07",
        "2017-06-16",
        "2017-06-17",
        "2017-06-23",
        "2017-06-24",
        "2017-06-28"
      ]
    },
    {
      "firstName":"Portia",
      "lastName":"Schommer",
      "email":"pschommer@hubspotpartners.com",
      "country":"France",
      "availableDates":[
        "2017-06-15",
        "2017-06-16",
        "2017-06-17",
        "2017-06-23",
        "2017-06-24",
        "2017-06-26",
        "2017-06-28"
      ]
    },
    {
      "firstName":"Jeanmarie",
      "lastName":"Boothe",
      "email":"jboothe@hubspotpartners.com",
      "country":"France",
      "availableDates":[
        "2017-06-05",
        "2017-06-16",
        "2017-06-17",
        "2017-06-20",
        "2017-06-23",
        "2017-06-24",
        "2017-06-28"
      ]
    },
    {
      "firstName":"Cheree",
      "lastName":"Ryburn",
      "email":"cryburn@hubspotpartners.com",
      "country":"France",
      "availableDates":[
        "2017-06-07",
        "2017-06-12",
        "2017-06-16",
        "2017-06-17",
        "2017-06-21",
        "2017-06-23",
        "2017-06-24",
        "2017-06-27",
        "2017-06-28"
      ]
    },
    {
      "firstName":"Johana",
      "lastName":"Lourens",
      "email":"jlourens@hubspotpartners.com",
      "country":"France",
      "availableDates":[
        "2017-06-12",
        "2017-06-16",
        "2017-06-17",
        "2017-06-22",
        "2017-06-23",
        "2017-06-24",
        "2017-06-28"
      ]
    },
    {
      "firstName":"Melodi",
      "lastName":"Siebenaler",
      "email":"msiebenaler@hubspotpartners.com",
      "country":"France",
      "availableDates":[
        "2017-06-16",
        "2017-06-17",
        "2017-06-20",
        "2017-06-22",
        "2017-06-23",
        "2017-06-24",
        "2017-06-28"
      ]
    },
    {
      "firstName":"Benton",
      "lastName":"Milton",
      "email":"bmilton@hubspotpartners.com",
      "country":"France",
      "availableDates":[
        "2017-06-05",
        "2017-06-07",
        "2017-06-10",
        "2017-06-13",
        "2017-06-16",
        "2017-06-17",
        "2017-06-23",
        "2017-06-24",
        "2017-06-28"
      ]
    },
    {
      "firstName":"Val",
      "lastName":"Rivinius",
      "email":"vrivinius@hubspotpartners.com",
      "country":"France",
      "availableDates":[
        "2017-06-06",
        "2017-06-07",
        "2017-06-16",
        "2017-06-17",
        "2017-06-23",
        "2017-06-24",
        "2017-06-28"
      ]
    },
    {
      "firstName":"Rochel",
      "lastName":"Mcirvin",
      "email":"rmcirvin@hubspotpartners.com",
      "country":"France",
      "availableDates":[
        "2017-06-05",
        "2017-06-07",
        "2017-06-09",
        "2017-06-12",
        "2017-06-16",
        "2017-06-17",
        "2017-06-19",
        "2017-06-21",
        "2017-06-23",
        "2017-06-24",
        "2017-06-28"
      ]
    },
    {
      "firstName":"Marc",
      "lastName":"Keilen",
      "email":"mkeilen@hubspotpartners.com",
      "country":"France",
      "availableDates":[
        "2017-06-09",
        "2017-06-16",
        "2017-06-17",
        "2017-06-19",
        "2017-06-20",
        "2017-06-22",
        "2017-06-23",
        "2017-06-24",
        "2017-06-28"
      ]
    },
    {
      "firstName":"Francisca",
      "lastName":"Weiner",
      "email":"fweiner@hubspotpartners.com",
      "country":"France",
      "availableDates":[
        "2017-06-09",
        "2017-06-19",
        "2017-06-21",
        "2017-06-28"
      ]
    },
    {
      "firstName":"Fabian",
      "lastName":"Tabler",
      "email":"ftabler@hubspotpartners.com",
      "country":"France",
      "availableDates":[
        "2017-06-05",
        "2017-06-28",
        "2017-06-29"
      ]
    },
    {
      "firstName":"Virginia",
      "lastName":"Dalitz",
      "email":"vdalitz@hubspotpartners.com",
      "country":"France",
      "availableDates":[
        "2017-06-07",
        "2017-06-11",
        "2017-06-18",
        "2017-06-19",
        "2017-06-28"
      ]
    },
    {
      "firstName":"Katharine",
      "lastName":"Shawver",
      "email":"kshawver@hubspotpartners.com",
      "country":"France",
      "availableDates":[
        "2017-06-05",
        "2017-06-07",
        "2017-06-09",
        "2017-06-10",
        "2017-06-14",
        "2017-06-18",
        "2017-06-20",
        "2017-06-22",
        "2017-06-28"
      ]
    },
    {
      "firstName":"Syble",
      "lastName":"Nooner",
      "email":"snooner@hubspotpartners.com",
      "country":"France",
      "availableDates":[
        "2017-06-19",
        "2017-06-22",
        "2017-06-28"
      ]
    },
    {
      "firstName":"Marion",
      "lastName":"Hyzer",
      "email":"mhyzer@hubspotpartners.com",
      "country":"France",
      "availableDates":[
        "2017-06-05",
        "2017-06-06",
        "2017-06-14",
        "2017-06-22",
        "2017-06-28"
      ]
    },
    {
      "firstName":"Lyda",
      "lastName":"Wagenheim",
      "email":"lwagenheim@hubspotpartners.com",
      "country":"France",
      "availableDates":[
        "2017-06-05",
        "2017-06-09",
        "2017-06-19",
        "2017-06-22",
        "2017-06-28"
      ]
    },
    {
      "firstName":"Tiffany",
      "lastName":"Genova",
      "email":"tgenova@hubspotpartners.com",
      "country":"France",
      "availableDates":[
        "2017-06-06",
        "2017-06-18",
        "2017-06-28"
      ]
    },
    {
      "firstName":"Candy",
      "lastName":"Raethke",
      "email":"craethke@hubspotpartners.com",
      "country":"France",
      "availableDates":[
        "2017-06-07",
        "2017-06-19",
        "2017-06-21",
        "2017-06-22",
        "2017-06-28"
      ]
    },
    {
      "firstName":"Amalia",
      "lastName":"Parady",
      "email":"aparady@hubspotpartners.com",
      "country":"France",
      "availableDates":[
        "2017-06-05",
        "2017-06-07",
        "2017-06-08",
        "2017-06-21",
        "2017-06-28"
      ]
    }
  ]
}